ezcode/__init__.py
ezcode/Array/Interval.py
ezcode/Array/Merge.py
ezcode/Array/Search.py
ezcode/Array/Sort.py
ezcode/Array/Sub.py
ezcode/Array/Tail.py
ezcode/Array/Utils.py
ezcode/Array/__init__.py
ezcode/Cache/LRUCache.py
ezcode/Cache/__init__.py
ezcode/Dynamic/Knapsack.py
ezcode/Dynamic/SparseTable.py
ezcode/Dynamic/__init__.py
ezcode/Graph/DirectedGraph.py
ezcode/Graph/Graph.py
ezcode/Graph/GraphEdgeIterator.py
ezcode/Graph/GraphPathFinder.py
ezcode/Graph/UndirectedGraph.py
ezcode/Graph/__init__.py
ezcode/Grid/GridIterator.py
ezcode/Grid/GridPathFinder.py
ezcode/Grid/__init__.py
ezcode/Heap/PriorityMap.py
ezcode/Heap/PriorityQueue.py
ezcode/Heap/PriorityQueueOnPartialArray.py
ezcode/Heap/__init__.py
ezcode/List/DoublyLinkedList.py
ezcode/List/LinkedList.py
ezcode/List/LinkedListConstant.py
ezcode/List/LinkedListIterator.py
ezcode/List/LinkedListPrinter.py
ezcode/List/TailedLinkedList.py
ezcode/List/__init__.py
ezcode/Map/TreeMap.py
ezcode/Map/__init__.py
ezcode/Math/Calculator.py
ezcode/Math/Combination.py
ezcode/Math/Enumeration.py
ezcode/Math/Partition.py
ezcode/Math/Permutation.py
ezcode/Math/__init__.py
ezcode/Queue/MonotonicQueue.py
ezcode/Queue/Queue.py
ezcode/Queue/QueueOnPartialArray.py
ezcode/Queue/__init__.py
ezcode/Random/RandomDict.py
ezcode/Random/RandomIndex.py
ezcode/Random/RandomSet.py
ezcode/Random/Shuffle.py
ezcode/Random/__init__.py
ezcode/Set/TreeSet.py
ezcode/Set/__init__.py
ezcode/Stack/MinMaxStack.py
ezcode/Stack/MonotonicStack.py
ezcode/Stack/PersistentStack.py
ezcode/Stack/Stack.py
ezcode/Stack/StackOnPartialArray.py
ezcode/Stack/__init__.py
ezcode/Tree/AVLTree.py
ezcode/Tree/BinarySearchTree.py
ezcode/Tree/BinaryTree.py
ezcode/Tree/BinaryTreeConstant.py
ezcode/Tree/BinaryTreeIterator.py
ezcode/Tree/BinaryTreePrinter.py
ezcode/Tree/DecisionTree.py
ezcode/Tree/FileSystem.py
ezcode/Tree/RedBlackTree.py
ezcode/Tree/RedBlackTreeWithParent.py
ezcode/Tree/SegmentTree.py
ezcode/Tree/Trie.py
ezcode/Tree/__init__.py
ezcode-1.0.28.dist-info/LICENSE.md
ezcode-1.0.28.dist-info/METADATA
ezcode-1.0.28.dist-info/WHEEL
ezcode-1.0.28.dist-info/top_level.txt
ezcode-1.0.28.dist-info/RECORD
