Metadata-Version: 2.1
Name: ezcode
Version: 1.0.28
Summary: Easy Algorithm & Data Structure
Home-page: https://github.com/zheng-gao/ez_code
Author: Zheng Gao
Author-email: mail.zheng.gao@gmail.com
Project-URL: Documentation, https://github.com/zheng-gao/ez_code/blob/main/docs/readme.md
Project-URL: Bug Tracker, https://github.com/zheng-gao/ez_code/issues
Classifier: Programming Language :: Python :: 3
Classifier: License :: OSI Approved :: MIT License
Classifier: Operating System :: OS Independent
Requires-Python: >=3.10
License-File: LICENSE.md
